[{"idFlight":472,"origin":"CHUQUISACA","destination":"COCHABAMBA","airline":"BOLIVIANA_DE_AVIACION","departureDate":[2023,10,11,6,20,15,421327860],"arrivalDate":[2023,10,11,12,20,31,421327860],"cost":530},{"idFlight":824,"origin":"LA_PAZ","destination":"PANDO","airline":"TRANSPORTES_AEREOS_BOLIVIANOS","departureDate":[2023,9,11,13,43,3,468919857],"arrivalDate":[2023,9,11,19,31,47,468919857],"cost":699},{"idFlight":392,"origin":"PANDO","destination":"POTOSI","airline":"LINEA_AEREA_AMASZONAS","departureDate":[2024,2,2,23,49,47,476672455],"arrivalDate":[2024,2,3,6,35,35,476672455],"cost":541},{"idFlight":743,"origin":"LA_PAZ","destination":"POTOSI","airline":"LINEA_AEREA_AMASZONAS","departureDate":[2023,11,8,16,58,7,477523313],"arrivalDate":[2023,11,8,20,47,48,477523313],"cost":726},{"idFlight":97,"origin":"POTOSI","destination":"ORURO","airline":"BOLIVIANA_DE_AVIACION","departureDate":[2024,2,7,23,58,55,478394022],"arrivalDate":[2024,2,8,0,13,13,478394022],"cost":605}]