{"id":"584af83a-a219-4fcf-bcaa-43c6b0410cf1","keysNumber":10,"isLeaf":true,"order":10,"keys":[{"id":9635459,"name":"AMANDA","lastName":"SALCEDO","country":"BOLIVIA","category":"VIP"},{"id":9636741,"name":"VERONICA","lastName":"REYES","country":"BRASIL","category":"VIP"},{"id":9708772,"name":"JULIANA","lastName":"SOLIS","country":"ARGENTINA","category":"FREQUENT_PASSENGER"},{"id":9729822,"name":"OLGA","lastName":"GONZALEZ","country":"COSTA_RICA","category":"FREQUENT_PASSENGER"},{"id":9759108,"name":"VANESA","lastName":"MENDEZ","country":"BRASIL","category":"VIP"},{"id":9761938,"name":"GABRIELA","lastName":"PARDO","country":"CHILE","category":"FREQUENT_PASSENGER"},{"id":9765568,"name":"FELIPE","lastName":"URIBE","country":"MEXICO","category":"FREQUENT_PASSENGER"},{"id":9848239,"name":"EMILIO","lastName":"TORRES","country":"HONDURAS","category":"FREQUENT_PASSENGER"},{"id":9889274,"name":"ANGELICA","lastName":"SEPULVEDA","country":"PANAMA","category":"FREQUENT_PASSENGER"},{"id":9897314,"name":"RICARDO","lastName":"ARIAS","country":"EL_SALVADOR","category":"VIP"}],"childrenIds":[null,null,null,null,null,null,null,null,null,null,null,null,null,null,null,null,null,null,null,null]}