{"id":"6e3a9664-89d9-443b-a002-9864dd842249","keysNumber":14,"isLeaf":true,"order":10,"keys":[{"id":2762020,"name":"LUCIANA","lastName":"COLLAO","country":"CHILE","category":"REGULAR_PASSENGER"},{"id":2777355,"name":"ELENA","lastName":"PARRA","country":"EL_SALVADOR","category":"FREQUENT_PASSENGER"},{"id":2788759,"name":"LETICIA","lastName":"PINEDA","country":"CUBA","category":"VIP"},{"id":2819689,"name":"TOMAS","lastName":"JIMENEZ","country":"NICARAGUA","category":"FREQUENT_PASSENGER"},{"id":2847901,"name":"MIGUEL","lastName":"MIRANDA","country":"CUBA","category":"FREQUENT_PASSENGER"},{"id":2867349,"name":"NATALIA","lastName":"PINTO","country":"GUATEMALA","category":"REGULAR_PASSENGER"},{"id":2907611,"name":"JORGE","lastName":"RIVERA","country":"COLOMBIA","category":"VIP"},{"id":2928632,"name":"MARIA","lastName":"HERRERA","country":"CHILE","category":"FREQUENT_PASSENGER"},{"id":2945013,"name":"PABLO","lastName":"TORRES","country":"ECUADOR","category":"FREQUENT_PASSENGER"},{"id":2984768,"name":"CONSTANZA","lastName":"MIRANDA","country":"ARGENTINA","category":"VIP"},{"id":2985549,"name":"BRUNO","lastName":"JIMENEZ","country":"CUBA","category":"FREQUENT_PASSENGER"},{"id":3034228,"name":"JAZMIN","lastName":"AGUILERA","country":"PARAGUAY","category":"REGULAR_PASSENGER"},{"id":3060689,"name":"CONSTANZA","lastName":"GARCIA","country":"CHILE","category":"REGULAR_PASSENGER"},{"id":3088162,"name":"GUSTAVO","lastName":"MENDOZA","country":"MEXICO","category":"FREQUENT_PASSENGER"}],"childrenIds":[null,null,null,null,null,null,null,null,null,null,null,null,null,null,null,null,null,null,null,null]}