{"id":"7bd5d6c5-e5f3-4488-a90a-038ddae153d8","keysNumber":13,"isLeaf":true,"order":10,"keys":[{"id":5814676,"name":"ROSA","lastName":"FONSECA","country":"PERU","category":"VIP"},{"id":5826969,"name":"VERONICA","lastName":"GUZMAN","country":"CHILE","category":"REGULAR_PASSENGER"},{"id":5846363,"name":"VALERIO","lastName":"CAMPOS","country":"PANAMA","category":"REGULAR_PASSENGER"},{"id":5847753,"name":"ISABELLA","lastName":"RIVAS","country":"ARGENTINA","category":"REGULAR_PASSENGER"},{"id":5850840,"name":"MANUEL","lastName":"SOLIS","country":"PARAGUAY","category":"VIP"},{"id":5881862,"name":"JULIANA","lastName":"CORREA","country":"ARGENTINA","category":"REGULAR_PASSENGER"},{"id":5927701,"name":"SEBASTIAN","lastName":"ANDRADE","country":"MEXICO","category":"VIP"},{"id":5954059,"name":"JOSE","lastName":"GUZMAN","country":"PERU","category":"REGULAR_PASSENGER"},{"id":5981917,"name":"RUBEN","lastName":"BARROS","country":"CUBA","category":"FREQUENT_PASSENGER"},{"id":5999926,"name":"EVA","lastName":"SANCHEZ","country":"ARGENTINA","category":"FREQUENT_PASSENGER"},{"id":6030700,"name":"VALENTIN","lastName":"PACHECO","country":"BOLIVIA","category":"FREQUENT_PASSENGER"},{"id":6076115,"name":"JAVIER","lastName":"OCHOA","country":"PARAGUAY","category":"FREQUENT_PASSENGER"},{"id":6105719,"name":"CECILIA","lastName":"PINEDA","country":"PARAGUAY","category":"VIP"}],"childrenIds":[null,null,null,null,null,null,null,null,null,null,null,null,null,null,null,null,null,null,null,null]}